cepton_sdk3/__init__.py
cepton_sdk3/c.py
cepton_sdk3/frame.py
cepton_sdk3/sdk.py
cepton_sdk3/sensor.py
cepton_sdk3/soa.py
cepton_sdk3/lib/linux-arm64/libcepton_sdk3.so
cepton_sdk3/lib/linux-x64/libcepton_sdk3.so
cepton_sdk3/lib/win-x64/cepton_sdk3.dll
cepton_sdk3/lib/win-x64/cepton_sdk3.dll.lib
cepton_sdk3/utils/__init__.py
cepton_sdk3/utils/io.py
cepton_sdk3-3.0.17.14.post1.dist-info/METADATA
cepton_sdk3-3.0.17.14.post1.dist-info/WHEEL
cepton_sdk3-3.0.17.14.post1.dist-info/licenses/LICENSE
cepton_sdk3-3.0.17.14.post1.dist-info/RECORD
