Metadata-Version: 2.4
Name: cepton-sdk3
Version: 3.0.17.14.post1
Summary: Cepton SDK3
Author-email: Will Lauer <will.lauer@cepton.com>, Dongyi Liao <dongyi.liao@cepton.com>
Maintainer-email: Will Lauer <will.lauer@cepton.com>
License-Expression: MIT
License-File: LICENSE
Requires-Dist: numpy>=1.21
